package me.frep.aegisguard.spigot.AegisGuard_KZ;

public final class aegisguard_KZ {
  public static final short aegisguard_h = -24768;
  
  public static final short aegisguard_c = -23769;
  
  public static final short aegisguard_Z = -30768;
  
  public static final short aegisguard_O = -29769;
  
  public static final short aegisguard_w = -29768;
  
  public static final short aegisguard_X = -28769;
  
  public static final short aegisguard_r = -28768;
  
  public static final short aegisguard_H = -27769;
  
  public static final short aegisguard_B = -27768;
  
  public static final short aegisguard_U = -26769;
  
  public static final short aegisguard_s = -26768;
  
  public static final short aegisguard_W = -25769;
  
  public static final short aegisguard_F = -23768;
  
  public static final short aegisguard_l = -22769;
  
  public static final short aegisguard_i = -22768;
  
  public static final short aegisguard_K = -21769;
  
  private static final String a;
  
  private aegisguard_KZ() {
    throw new UnsupportedOperationException(a);
  }
  
  static {
    // Byte code:
    //   0: bipush #22
    //   2: ldc 'xs5KY.\\fzH3Y1Eof\\b\<_hH'T}Oz(D}N~H/C)Mu/\\nD8H'
    //   4: iconst_m1
    //   5: goto -> 14
    //   8: putstatic me/frep/aegisguard/spigot/aegisguard_KZ.a : Ljava/lang/String;
    //   11: goto -> 154
    //   14: dup_x2
    //   15: pop
    //   16: invokevirtual toCharArray : ()[C
    //   19: dup_x1
    //   20: arraylength
    //   21: dup_x2
    //   22: pop
    //   23: iconst_0
    //   24: istore_0
    //   25: dup2_x1
    //   26: pop2
    //   27: dup_x2
    //   28: iconst_1
    //   29: if_icmpgt -> 128
    //   32: dup2
    //   33: swap
    //   34: iload_0
    //   35: dup2_x1
    //   36: caload
    //   37: swap
    //   38: iload_0
    //   39: bipush #7
    //   41: irem
    //   42: tableswitch default -> 110, 0 -> 80, 1 -> 85, 2 -> 90, 3 -> 95, 4 -> 100, 5 -> 105
    //   80: bipush #58
    //   82: goto -> 112
    //   85: bipush #13
    //   87: goto -> 112
    //   90: bipush #126
    //   92: goto -> 112
    //   95: bipush #80
    //   97: goto -> 112
    //   100: bipush #125
    //   102: goto -> 112
    //   105: bipush #38
    //   107: goto -> 112
    //   110: bipush #75
    //   112: ixor
    //   113: ixor
    //   114: i2c
    //   115: castore
    //   116: iinc #0, 1
    //   119: dup
    //   120: ifne -> 128
    //   123: dup2
    //   124: dup_x1
    //   125: goto -> 35
    //   128: dup2_x1
    //   129: pop2
    //   130: dup_x2
    //   131: iload_0
    //   132: if_icmpgt -> 32
    //   135: pop
    //   136: new java/lang/String
    //   139: dup_x1
    //   140: swap
    //   141: invokespecial <init> : ([C)V
    //   144: invokevirtual intern : ()Ljava/lang/String;
    //   147: swap
    //   148: pop
    //   149: swap
    //   150: pop
    //   151: goto -> 8
    //   154: return
  }
}
