package me.frep.aegisguard.spigot.AegisGuard_R;

import java.lang.invoke.MethodHandles;
import java.util.ArrayDeque;
import me.frep.aegisguard.spigot.aegisguard_e;
import me.frep.aegisguard.spigot.aegisguard_hu;
import org.bukkit.util.Vector;

public class aegisguard_R {
  private final aegisguard_hu aegisguard_e;
  
  private float aegisguard_d;
  
  private float aegisguard_O;
  
  private float aegisguard_D;
  
  private float aegisguard_V;
  
  private float aegisguard_l;
  
  private float aegisguard_X;
  
  private float aegisguard_P;
  
  private float aegisguard__;
  
  private float aegisguard_a;
  
  private float aegisguard_q;
  
  private float aegisguard_Q;
  
  private float aegisguard_N;
  
  private float aegisguard_U;
  
  private float aegisguard_E;
  
  private float aegisguard_y;
  
  private float aegisguard_M;
  
  private float aegisguard_f;
  
  private float aegisguard_G;
  
  private boolean aegisguard_p;
  
  private boolean aegisguard_W;
  
  private boolean aegisguard_x;
  
  private double aegisguard_s;
  
  private double aegisguard_n;
  
  public aegisguard_hu aegisguard_a(Object[] paramArrayOfObject) {
    return this.aegisguard_e;
  }
  
  public float aegisguard_P(Object[] paramArrayOfObject) {
    return this.aegisguard_d;
  }
  
  public float aegisguard_A(Object[] paramArrayOfObject) {
    return this.aegisguard_O;
  }
  
  public float aegisguard_D(Object[] paramArrayOfObject) {
    return this.aegisguard_D;
  }
  
  public float aegisguard_d(Object[] paramArrayOfObject) {
    return this.aegisguard_V;
  }
  
  public float aegisguard_Q(Object[] paramArrayOfObject) {
    return this.aegisguard_l;
  }
  
  public float aegisguard_N(Object[] paramArrayOfObject) {
    return this.aegisguard_X;
  }
  
  public float aegisguard_G(Object[] paramArrayOfObject) {
    return this.aegisguard_P;
  }
  
  public float aegisguard_t(Object[] paramArrayOfObject) {
    return this.aegisguard__;
  }
  
  public float aegisguard_m(Object[] paramArrayOfObject) {
    return this.aegisguard_a;
  }
  
  public float aegisguard_X(Object[] paramArrayOfObject) {
    return this.aegisguard_q;
  }
  
  public float aegisguard_q(Object[] paramArrayOfObject) {
    return this.aegisguard_Q;
  }
  
  public float aegisguard_H(Object[] paramArrayOfObject) {
    return this.aegisguard_N;
  }
  
  public float aegisguard_Y(Object[] paramArrayOfObject) {
    return this.aegisguard_U;
  }
  
  public float aegisguard_o(Object[] paramArrayOfObject) {
    return this.aegisguard_E;
  }
  
  public float aegisguard_J(Object[] paramArrayOfObject) {
    return this.aegisguard_y;
  }
  
  public float aegisguard__(Object[] paramArrayOfObject) {
    return this.aegisguard_M;
  }
  
  public float aegisguard_x(Object[] paramArrayOfObject) {
    return this.aegisguard_f;
  }
  
  public float aegisguard_v(Object[] paramArrayOfObject) {
    return this.aegisguard_G;
  }
  
  public boolean aegisguard_I(Object[] paramArrayOfObject) {
    return this.aegisguard_p;
  }
  
  public boolean aegisguard_T(Object[] paramArrayOfObject) {
    return this.aegisguard_W;
  }
  
  public boolean aegisguard_E(Object[] paramArrayOfObject) {
    return this.aegisguard_x;
  }
  
  public double aegisguard_v(Object[] paramArrayOfObject) {
    return this.aegisguard_s;
  }
  
  public double aegisguard_I(Object[] paramArrayOfObject) {
    return this.aegisguard_n;
  }
  
  private final ArrayDeque aegisguard_T = new ArrayDeque();
  
  private int aegisguard_v;
  
  private int aegisguard_z;
  
  private int aegisguard_i;
  
  private int aegisguard_R;
  
  private int aegisguard_t;
  
  private int aegisguard_A;
  
  private static int aegisguard_h;
  
  private static final long a = aegisguard_e.a(-6605869709928735146L, -5246074155169513107L, MethodHandles.lookup().lookupClass()).a(39481943862007L);
  
  public ArrayDeque aegisguard_m(Object[] paramArrayOfObject) {
    return this.aegisguard_T;
  }
  
  public int aegisguard_M(Object[] paramArrayOfObject) {
    return this.aegisguard_v;
  }
  
  public int aegisguard_m(Object[] paramArrayOfObject) {
    return this.aegisguard_z;
  }
  
  public int aegisguard_L(Object[] paramArrayOfObject) {
    return this.aegisguard_i;
  }
  
  public int aegisguard_q(Object[] paramArrayOfObject) {
    return this.aegisguard_R;
  }
  
  public int aegisguard_H(Object[] paramArrayOfObject) {
    return this.aegisguard_t;
  }
  
  public int aegisguard_y(Object[] paramArrayOfObject) {
    return this.aegisguard_A;
  }
  
  public aegisguard_R(aegisguard_hu paramaegisguard_hu) {
    this.aegisguard_e = paramaegisguard_hu;
  }
  
  public void aegisguard_o(Object[] paramArrayOfObject) {
    // Byte code:
    //   0: aload_1
    //   1: dup
    //   2: iconst_0
    //   3: aaload
    //   4: checkcast java/lang/Long
    //   7: invokevirtual longValue : ()J
    //   10: lstore_2
    //   11: dup
    //   12: iconst_1
    //   13: aaload
    //   14: checkcast java/lang/Float
    //   17: invokevirtual floatValue : ()F
    //   20: fstore #4
    //   22: dup
    //   23: iconst_2
    //   24: aaload
    //   25: checkcast java/lang/Float
    //   28: invokevirtual floatValue : ()F
    //   31: fstore #5
    //   33: pop
    //   34: getstatic me/frep/aegisguard/spigot/aegisguard_R.a : J
    //   37: lload_2
    //   38: lxor
    //   39: lstore_2
    //   40: lload_2
    //   41: dup2
    //   42: ldc2_w 42306356739605
    //   45: lxor
    //   46: lstore #6
    //   48: dup2
    //   49: ldc2_w 41176930017839
    //   52: lxor
    //   53: lstore #8
    //   55: pop2
    //   56: aload_0
    //   57: aload_0
    //   58: getfield aegisguard_d : F
    //   61: putfield aegisguard_D : F
    //   64: aload_0
    //   65: aload_0
    //   66: getfield aegisguard_O : F
    //   69: putfield aegisguard_V : F
    //   72: invokestatic aegisguard_P : ()[Lme/frep/aegisguard/spigot/check/AbstractCheck;
    //   75: aload_0
    //   76: fload #4
    //   78: putfield aegisguard_d : F
    //   81: aload_0
    //   82: fload #5
    //   84: putfield aegisguard_O : F
    //   87: aload_0
    //   88: aload_0
    //   89: getfield aegisguard_l : F
    //   92: putfield aegisguard_P : F
    //   95: aload_0
    //   96: aload_0
    //   97: getfield aegisguard_X : F
    //   100: putfield aegisguard__ : F
    //   103: aload_0
    //   104: fload #4
    //   106: aload_0
    //   107: getfield aegisguard_D : F
    //   110: fsub
    //   111: invokestatic abs : (F)F
    //   114: putfield aegisguard_l : F
    //   117: aload_0
    //   118: fload #5
    //   120: aload_0
    //   121: getfield aegisguard_V : F
    //   124: fsub
    //   125: invokestatic abs : (F)F
    //   128: putfield aegisguard_X : F
    //   131: aload_0
    //   132: aload_0
    //   133: getfield aegisguard_q : F
    //   136: putfield aegisguard_N : F
    //   139: aload_0
    //   140: aload_0
    //   141: getfield aegisguard_a : F
    //   144: putfield aegisguard_Q : F
    //   147: astore #10
    //   149: aload_0
    //   150: aload_0
    //   151: getfield aegisguard_l : F
    //   154: aload_0
    //   155: getfield aegisguard_P : F
    //   158: fsub
    //   159: invokestatic abs : (F)F
    //   162: putfield aegisguard_a : F
    //   165: aload_0
    //   166: aload_0
    //   167: getfield aegisguard_X : F
    //   170: aload_0
    //   171: getfield aegisguard__ : F
    //   174: fsub
    //   175: invokestatic abs : (F)F
    //   178: putfield aegisguard_q : F
    //   181: aload_0
    //   182: getfield aegisguard_n : D
    //   185: d2f
    //   186: ldc 0.6
    //   188: fmul
    //   189: ldc 0.2
    //   191: fadd
    //   192: fstore #11
    //   194: fload #11
    //   196: fload #11
    //   198: fmul
    //   199: fload #11
    //   201: fmul
    //   202: ldc 1.2
    //   204: fmul
    //   205: fstore #12
    //   207: aload_0
    //   208: aload_0
    //   209: getfield aegisguard_l : F
    //   212: fload #12
    //   214: fdiv
    //   215: putfield aegisguard_U : F
    //   218: aload_0
    //   219: aload_0
    //   220: getfield aegisguard_X : F
    //   223: fload #12
    //   225: fdiv
    //   226: putfield aegisguard_E : F
    //   229: aload_0
    //   230: aload_0
    //   231: getfield aegisguard_l : F
    //   234: fload #12
    //   236: fdiv
    //   237: f2i
    //   238: putfield aegisguard_t : I
    //   241: aload_0
    //   242: aload_0
    //   243: getfield aegisguard_X : F
    //   246: fload #12
    //   248: fdiv
    //   249: f2i
    //   250: putfield aegisguard_A : I
    //   253: aload_0
    //   254: lload #6
    //   256: iconst_1
    //   257: anewarray java/lang/Object
    //   260: dup_x2
    //   261: dup_x2
    //   262: pop
    //   263: invokestatic valueOf : (J)Ljava/lang/Long;
    //   266: iconst_0
    //   267: swap
    //   268: aastore
    //   269: invokespecial aegisguard_F : ([Ljava/lang/Object;)V
    //   272: ldc 0.512
    //   274: fstore #13
    //   276: ldc 1.073742
    //   278: fstore #14
    //   280: aload_0
    //   281: getfield aegisguard_l : F
    //   284: ldc 1.073742
    //   286: fmul
    //   287: aload_0
    //   288: getfield aegisguard_l : F
    //   291: f2d
    //   292: ldc2_w 0.15
    //   295: dadd
    //   296: d2f
    //   297: fadd
    //   298: fstore #15
    //   300: aload_0
    //   301: getfield aegisguard_X : F
    //   304: ldc 1.073742
    //   306: fmul
    //   307: aload_0
    //   308: getfield aegisguard_X : F
    //   311: f2d
    //   312: ldc2_w 0.15
    //   315: dsub
    //   316: d2f
    //   317: fsub
    //   318: fstore #16
    //   320: aload_0
    //   321: getfield aegisguard_X : F
    //   324: fload #16
    //   326: fsub
    //   327: invokestatic abs : (F)F
    //   330: fstore #17
    //   332: aload_0
    //   333: getfield aegisguard_l : F
    //   336: fload #15
    //   338: fsub
    //   339: invokestatic abs : (F)F
    //   342: fstore #18
    //   344: aload_0
    //   345: aload_0
    //   346: getfield aegisguard_y : F
    //   349: putfield aegisguard_f : F
    //   352: aload_0
    //   353: aload_0
    //   354: getfield aegisguard_M : F
    //   357: putfield aegisguard_G : F
    //   360: aload_0
    //   361: aload_0
    //   362: getfield aegisguard_X : F
    //   365: fload #17
    //   367: fsub
    //   368: invokestatic abs : (F)F
    //   371: putfield aegisguard_y : F
    //   374: aload_0
    //   375: aload_0
    //   376: getfield aegisguard_l : F
    //   379: fload #18
    //   381: fsub
    //   382: invokestatic abs : (F)F
    //   385: putfield aegisguard_M : F
    //   388: aload_0
    //   389: getfield aegisguard_X : F
    //   392: f2d
    //   393: ldc2_w 0.1
    //   396: dcmpl
    //   397: aload #10
    //   399: ifnull -> 444
    //   402: ifle -> 466
    //   405: goto -> 412
    //   408: invokestatic a : (Ljava/lang/RuntimeException;)Ljava/lang/RuntimeException;
    //   411: athrow
    //   412: aload_0
    //   413: aload #10
    //   415: lload_2
    //   416: lconst_0
    //   417: lcmp
    //   418: iflt -> 463
    //   421: ifnull -> 448
    //   424: goto -> 431
    //   427: invokestatic a : (Ljava/lang/RuntimeException;)Ljava/lang/RuntimeException;
    //   430: athrow
    //   431: getfield aegisguard_X : F
    //   434: ldc 25.0
    //   436: fcmpg
    //   437: goto -> 444
    //   440: invokestatic a : (Ljava/lang/RuntimeException;)Ljava/lang/RuntimeException;
    //   443: athrow
    //   444: ifge -> 466
    //   447: aload_0
    //   448: lload #8
    //   450: iconst_1
    //   451: anewarray java/lang/Object
    //   454: dup_x2
    //   455: dup_x2
    //   456: pop
    //   457: invokestatic valueOf : (J)Ljava/lang/Long;
    //   460: iconst_0
    //   461: swap
    //   462: aastore
    //   463: invokespecial aegisguard_m : ([Ljava/lang/Object;)V
    //   466: return
    // Line number table:
    //   Java source line number -> byte code offset
    //   #36	-> 56
    //   #37	-> 64
    //   #39	-> 75
    //   #40	-> 81
    //   #42	-> 87
    //   #43	-> 95
    //   #45	-> 103
    //   #46	-> 117
    //   #48	-> 131
    //   #49	-> 139
    //   #51	-> 149
    //   #52	-> 165
    //   #54	-> 181
    //   #55	-> 194
    //   #57	-> 207
    //   #58	-> 218
    //   #60	-> 229
    //   #61	-> 241
    //   #63	-> 253
    //   #65	-> 272
    //   #66	-> 276
    //   #67	-> 280
    //   #68	-> 300
    //   #69	-> 320
    //   #70	-> 332
    //   #71	-> 344
    //   #72	-> 352
    //   #73	-> 360
    //   #74	-> 374
    //   #76	-> 388
    //   #77	-> 447
    //   #79	-> 466
    // Exception table:
    //   from	to	target	type
    //   344	405	408	java/lang/RuntimeException
    //   402	424	427	java/lang/RuntimeException
    //   412	437	440	java/lang/RuntimeException
  }
  
  public boolean aegisguard_u(Object[] paramArrayOfObject) {
    // Byte code:
    //   0: aload_1
    //   1: dup
    //   2: iconst_0
    //   3: aaload
    //   4: checkcast java/lang/Long
    //   7: invokevirtual longValue : ()J
    //   10: lstore_2
    //   11: pop
    //   12: getstatic me/frep/aegisguard/spigot/aegisguard_R.a : J
    //   15: lload_2
    //   16: lxor
    //   17: lstore_2
    //   18: invokestatic aegisguard_P : ()[Lme/frep/aegisguard/spigot/check/AbstractCheck;
    //   21: astore #4
    //   23: aload_0
    //   24: getfield aegisguard_v : I
    //   27: aload #4
    //   29: ifnull -> 53
    //   32: ifle -> 82
    //   35: goto -> 42
    //   38: invokestatic a : (Ljava/lang/RuntimeException;)Ljava/lang/RuntimeException;
    //   41: athrow
    //   42: aload_0
    //   43: getfield aegisguard_v : I
    //   46: goto -> 53
    //   49: invokestatic a : (Ljava/lang/RuntimeException;)Ljava/lang/RuntimeException;
    //   52: athrow
    //   53: aload #4
    //   55: ifnull -> 79
    //   58: sipush #200
    //   61: if_icmpge -> 82
    //   64: goto -> 71
    //   67: invokestatic a : (Ljava/lang/RuntimeException;)Ljava/lang/RuntimeException;
    //   70: athrow
    //   71: iconst_1
    //   72: goto -> 79
    //   75: invokestatic a : (Ljava/lang/RuntimeException;)Ljava/lang/RuntimeException;
    //   78: athrow
    //   79: goto -> 83
    //   82: iconst_0
    //   83: ireturn
    // Line number table:
    //   Java source line number -> byte code offset
    //   #82	-> 23
    // Exception table:
    //   from	to	target	type
    //   23	35	38	java/lang/RuntimeException
    //   32	46	49	java/lang/RuntimeException
    //   53	64	67	java/lang/RuntimeException
    //   58	72	75	java/lang/RuntimeException
  }
  
  private void aegisguard_F(Object[] paramArrayOfObject) {
    // Byte code:
    //   0: aload_1
    //   1: dup
    //   2: iconst_0
    //   3: aaload
    //   4: checkcast java/lang/Long
    //   7: invokevirtual longValue : ()J
    //   10: lstore_2
    //   11: pop
    //   12: getstatic me/frep/aegisguard/spigot/aegisguard_R.a : J
    //   15: lload_2
    //   16: lxor
    //   17: lstore_2
    //   18: getstatic me/frep/aegisguard/spigot/aegisguard_K.INSTANCE : Lme/frep/aegisguard/spigot/aegisguard_K;
    //   21: invokevirtual aegisguard_W : ()Lme/frep/aegisguard/spigot/aegisguard_K8;
    //   24: iconst_0
    //   25: anewarray java/lang/Object
    //   28: invokevirtual aegisguard_I : ([Ljava/lang/Object;)I
    //   31: istore #5
    //   33: aload_0
    //   34: getfield aegisguard_l : F
    //   37: aload_0
    //   38: getfield aegisguard_P : F
    //   41: fsub
    //   42: invokestatic abs : (F)F
    //   45: fstore #6
    //   47: invokestatic aegisguard_P : ()[Lme/frep/aegisguard/spigot/check/AbstractCheck;
    //   50: aload_0
    //   51: getfield aegisguard_X : F
    //   54: aload_0
    //   55: getfield aegisguard__ : F
    //   58: fsub
    //   59: invokestatic abs : (F)F
    //   62: fstore #7
    //   64: fload #6
    //   66: aload_0
    //   67: getfield aegisguard_l : F
    //   70: fsub
    //   71: invokestatic abs : (F)F
    //   74: fstore #8
    //   76: fload #7
    //   78: aload_0
    //   79: getfield aegisguard_X : F
    //   82: fsub
    //   83: invokestatic abs : (F)F
    //   86: fstore #9
    //   88: astore #4
    //   90: fload #8
    //   92: f2d
    //   93: dconst_1
    //   94: dcmpl
    //   95: aload #4
    //   97: ifnull -> 163
    //   100: ifle -> 156
    //   103: goto -> 110
    //   106: invokestatic a : (Ljava/lang/RuntimeException;)Ljava/lang/RuntimeException;
    //   109: athrow
    //   110: fload #9
    //   112: f2d
    //   113: dconst_1
    //   114: dcmpl
    //   115: aload #4
    //   117: lload_2
    //   118: lconst_0
    //   119: lcmp
    //   120: ifle -> 165
    //   123: ifnull -> 163
    //   126: goto -> 133
    //   129: invokestatic a : (Ljava/lang/RuntimeException;)Ljava/lang/RuntimeException;
    //   132: athrow
    //   133: ifle -> 156
    //   136: goto -> 143
    //   139: invokestatic a : (Ljava/lang/RuntimeException;)Ljava/lang/RuntimeException;
    //   142: athrow
    //   143: aload_0
    //   144: iload #5
    //   146: putfield aegisguard_z : I
    //   149: goto -> 156
    //   152: invokestatic a : (Ljava/lang/RuntimeException;)Ljava/lang/RuntimeException;
    //   155: athrow
    //   156: aload_0
    //   157: getfield aegisguard_X : F
    //   160: ldc 20.0
    //   162: fcmpg
    //   163: aload #4
    //   165: ifnull -> 241
    //   168: ifge -> 225
    //   171: goto -> 178
    //   174: invokestatic a : (Ljava/lang/RuntimeException;)Ljava/lang/RuntimeException;
    //   177: athrow
    //   178: aload_0
    //   179: getfield aegisguard_s : D
    //   182: dconst_0
    //   183: dcmpg
    //   184: lload_2
    //   185: lconst_0
    //   186: lcmp
    //   187: ifle -> 241
    //   190: aload #4
    //   192: ifnull -> 241
    //   195: goto -> 202
    //   198: invokestatic a : (Ljava/lang/RuntimeException;)Ljava/lang/RuntimeException;
    //   201: athrow
    //   202: ifge -> 225
    //   205: goto -> 212
    //   208: invokestatic a : (Ljava/lang/RuntimeException;)Ljava/lang/RuntimeException;
    //   211: athrow
    //   212: aload_0
    //   213: iload #5
    //   215: putfield aegisguard_i : I
    //   218: goto -> 225
    //   221: invokestatic a : (Ljava/lang/RuntimeException;)Ljava/lang/RuntimeException;
    //   224: athrow
    //   225: aload_0
    //   226: aload #4
    //   228: ifnull -> 290
    //   231: getfield aegisguard_p : Z
    //   234: goto -> 241
    //   237: invokestatic a : (Ljava/lang/RuntimeException;)Ljava/lang/RuntimeException;
    //   240: athrow
    //   241: ifeq -> 289
    //   244: aload_0
    //   245: lload_2
    //   246: lconst_0
    //   247: lcmp
    //   248: iflt -> 290
    //   251: aload #4
    //   253: ifnull -> 290
    //   256: goto -> 263
    //   259: invokestatic a : (Ljava/lang/RuntimeException;)Ljava/lang/RuntimeException;
    //   262: athrow
    //   263: getfield aegisguard_W : Z
    //   266: ifeq -> 289
    //   269: goto -> 276
    //   272: invokestatic a : (Ljava/lang/RuntimeException;)Ljava/lang/RuntimeException;
    //   275: athrow
    //   276: aload_0
    //   277: iload #5
    //   279: putfield aegisguard_R : I
    //   282: goto -> 289
    //   285: invokestatic a : (Ljava/lang/RuntimeException;)Ljava/lang/RuntimeException;
    //   288: athrow
    //   289: aload_0
    //   290: iload #5
    //   292: aload_0
    //   293: getfield aegisguard_z : I
    //   296: lload_2
    //   297: lconst_0
    //   298: lcmp
    //   299: ifle -> 309
    //   302: isub
    //   303: aload #4
    //   305: ifnull -> 327
    //   308: iconst_3
    //   309: if_icmple -> 330
    //   312: goto -> 319
    //   315: invokestatic a : (Ljava/lang/RuntimeException;)Ljava/lang/RuntimeException;
    //   318: athrow
    //   319: iconst_1
    //   320: goto -> 327
    //   323: invokestatic a : (Ljava/lang/RuntimeException;)Ljava/lang/RuntimeException;
    //   326: athrow
    //   327: goto -> 331
    //   330: iconst_0
    //   331: putfield aegisguard_p : Z
    //   334: aload_0
    //   335: iload #5
    //   337: aload_0
    //   338: getfield aegisguard_i : I
    //   341: lload_2
    //   342: lconst_0
    //   343: lcmp
    //   344: ifle -> 354
    //   347: isub
    //   348: aload #4
    //   350: ifnull -> 372
    //   353: iconst_3
    //   354: if_icmpge -> 375
    //   357: goto -> 364
    //   360: invokestatic a : (Ljava/lang/RuntimeException;)Ljava/lang/RuntimeException;
    //   363: athrow
    //   364: iconst_1
    //   365: goto -> 372
    //   368: invokestatic a : (Ljava/lang/RuntimeException;)Ljava/lang/RuntimeException;
    //   371: athrow
    //   372: goto -> 376
    //   375: iconst_0
    //   376: putfield aegisguard_W : Z
    //   379: aload_0
    //   380: iload #5
    //   382: aload_0
    //   383: getfield aegisguard_R : I
    //   386: lload_2
    //   387: lconst_0
    //   388: lcmp
    //   389: ifle -> 400
    //   392: isub
    //   393: aload #4
    //   395: ifnull -> 418
    //   398: bipush #8
    //   400: if_icmpge -> 421
    //   403: goto -> 410
    //   406: invokestatic a : (Ljava/lang/RuntimeException;)Ljava/lang/RuntimeException;
    //   409: athrow
    //   410: iconst_1
    //   411: goto -> 418
    //   414: invokestatic a : (Ljava/lang/RuntimeException;)Ljava/lang/RuntimeException;
    //   417: athrow
    //   418: goto -> 422
    //   421: iconst_0
    //   422: putfield aegisguard_x : Z
    //   425: return
    // Line number table:
    //   Java source line number -> byte code offset
    //   #86	-> 18
    //   #88	-> 33
    //   #89	-> 50
    //   #91	-> 64
    //   #92	-> 76
    //   #94	-> 90
    //   #95	-> 156
    //   #96	-> 225
    //   #98	-> 289
    //   #99	-> 334
    //   #100	-> 379
    //   #101	-> 425
    // Exception table:
    //   from	to	target	type
    //   90	103	106	java/lang/RuntimeException
    //   100	126	129	java/lang/RuntimeException
    //   110	136	139	java/lang/RuntimeException
    //   133	149	152	java/lang/RuntimeException
    //   163	171	174	java/lang/RuntimeException
    //   168	195	198	java/lang/RuntimeException
    //   178	205	208	java/lang/RuntimeException
    //   202	218	221	java/lang/RuntimeException
    //   225	234	237	java/lang/RuntimeException
    //   241	256	259	java/lang/RuntimeException
    //   244	269	272	java/lang/RuntimeException
    //   263	282	285	java/lang/RuntimeException
    //   290	312	315	java/lang/RuntimeException
    //   308	320	323	java/lang/RuntimeException
    //   331	357	360	java/lang/RuntimeException
    //   353	365	368	java/lang/RuntimeException
    //   376	403	406	java/lang/RuntimeException
    //   398	411	414	java/lang/RuntimeException
  }
  
  private void aegisguard_m(Object[] paramArrayOfObject) {
    // Byte code:
    //   0: aload_1
    //   1: dup
    //   2: iconst_0
    //   3: aaload
    //   4: checkcast java/lang/Long
    //   7: invokevirtual longValue : ()J
    //   10: lstore_2
    //   11: pop
    //   12: getstatic me/frep/aegisguard/spigot/aegisguard_R.a : J
    //   15: lload_2
    //   16: lxor
    //   17: lstore_2
    //   18: lload_2
    //   19: dup2
    //   20: ldc2_w 111074374019834
    //   23: lxor
    //   24: lstore #4
    //   26: dup2
    //   27: ldc2_w 136033867521275
    //   30: lxor
    //   31: lstore #6
    //   33: dup2
    //   34: ldc2_w 57283705197088
    //   37: lxor
    //   38: lstore #8
    //   40: pop2
    //   41: aload_0
    //   42: getfield aegisguard_X : F
    //   45: f2d
    //   46: aload_0
    //   47: getfield aegisguard__ : F
    //   50: f2d
    //   51: lload #8
    //   53: iconst_3
    //   54: anewarray java/lang/Object
    //   57: dup_x2
    //   58: dup_x2
    //   59: pop
    //   60: invokestatic valueOf : (J)Ljava/lang/Long;
    //   63: iconst_2
    //   64: swap
    //   65: aastore
    //   66: dup_x2
    //   67: dup_x2
    //   68: pop
    //   69: invokestatic valueOf : (D)Ljava/lang/Double;
    //   72: iconst_1
    //   73: swap
    //   74: aastore
    //   75: dup_x2
    //   76: dup_x2
    //   77: pop
    //   78: invokestatic valueOf : (D)Ljava/lang/Double;
    //   81: iconst_0
    //   82: swap
    //   83: aastore
    //   84: invokestatic aegisguard_S : ([Ljava/lang/Object;)D
    //   87: d2f
    //   88: fstore #11
    //   90: invokestatic aegisguard_P : ()[Lme/frep/aegisguard/spigot/check/AbstractCheck;
    //   93: ldc2_w 0.8333
    //   96: fload #11
    //   98: f2d
    //   99: dmul
    //   100: invokestatic cbrt : (D)D
    //   103: dstore #12
    //   105: astore #10
    //   107: ldc2_w 1.666
    //   110: dload #12
    //   112: dmul
    //   113: ldc2_w 0.3333
    //   116: dsub
    //   117: dstore #14
    //   119: dload #14
    //   121: ldc2_w 200.0
    //   124: dmul
    //   125: dstore #16
    //   127: aload_0
    //   128: dload #16
    //   130: putfield aegisguard_s : D
    //   133: aload_0
    //   134: getfield aegisguard_T : Ljava/util/ArrayDeque;
    //   137: dload #16
    //   139: d2i
    //   140: invokestatic valueOf : (I)Ljava/lang/Integer;
    //   143: invokevirtual add : (Ljava/lang/Object;)Z
    //   146: pop
    //   147: aload_0
    //   148: getfield aegisguard_T : Ljava/util/ArrayDeque;
    //   151: invokevirtual size : ()I
    //   154: aload #10
    //   156: ifnull -> 240
    //   159: bipush #40
    //   161: if_icmpne -> 282
    //   164: goto -> 171
    //   167: invokestatic a : (Ljava/lang/RuntimeException;)Ljava/lang/RuntimeException;
    //   170: athrow
    //   171: aload_0
    //   172: aload_0
    //   173: getfield aegisguard_T : Ljava/util/ArrayDeque;
    //   176: lload #6
    //   178: iconst_2
    //   179: anewarray java/lang/Object
    //   182: dup_x2
    //   183: dup_x2
    //   184: pop
    //   185: invokestatic valueOf : (J)Ljava/lang/Long;
    //   188: iconst_1
    //   189: swap
    //   190: aastore
    //   191: dup_x1
    //   192: swap
    //   193: iconst_0
    //   194: swap
    //   195: aastore
    //   196: invokestatic aegisguard_L : ([Ljava/lang/Object;)I
    //   199: putfield aegisguard_v : I
    //   202: aload_0
    //   203: aload #10
    //   205: ifnull -> 276
    //   208: goto -> 215
    //   211: invokestatic a : (Ljava/lang/RuntimeException;)Ljava/lang/RuntimeException;
    //   214: athrow
    //   215: lload #4
    //   217: iconst_1
    //   218: anewarray java/lang/Object
    //   221: dup_x2
    //   222: dup_x2
    //   223: pop
    //   224: invokestatic valueOf : (J)Ljava/lang/Long;
    //   227: iconst_0
    //   228: swap
    //   229: aastore
    //   230: invokevirtual aegisguard_u : ([Ljava/lang/Object;)Z
    //   233: goto -> 240
    //   236: invokestatic a : (Ljava/lang/RuntimeException;)Ljava/lang/RuntimeException;
    //   239: athrow
    //   240: ifeq -> 275
    //   243: aload_0
    //   244: getstatic me/frep/aegisguard/spigot/aegisguard_a.aegisguard_c : Ljava/util/Map;
    //   247: aload_0
    //   248: getfield aegisguard_v : I
    //   251: invokestatic valueOf : (I)Ljava/lang/Integer;
    //   254: invokeinterface get : (Ljava/lang/Object;)Ljava/lang/Object;
    //   259: checkcast java/lang/Double
    //   262: invokevirtual doubleValue : ()D
    //   265: putfield aegisguard_n : D
    //   268: goto -> 275
    //   271: invokestatic a : (Ljava/lang/RuntimeException;)Ljava/lang/RuntimeException;
    //   274: athrow
    //   275: aload_0
    //   276: getfield aegisguard_T : Ljava/util/ArrayDeque;
    //   279: invokevirtual clear : ()V
    //   282: return
    // Line number table:
    //   Java source line number -> byte code offset
    //   #104	-> 41
    //   #105	-> 93
    //   #106	-> 107
    //   #107	-> 119
    //   #109	-> 127
    //   #111	-> 133
    //   #113	-> 147
    //   #114	-> 171
    //   #116	-> 202
    //   #118	-> 275
    //   #120	-> 282
    // Exception table:
    //   from	to	target	type
    //   127	164	167	java/lang/RuntimeException
    //   159	208	211	java/lang/RuntimeException
    //   171	233	236	java/lang/RuntimeException
    //   240	268	271	java/lang/RuntimeException
  }
  
  public boolean aegisguard_X(Object[] paramArrayOfObject) {
    // Byte code:
    //   0: aload_1
    //   1: dup
    //   2: iconst_0
    //   3: aaload
    //   4: checkcast java/lang/Long
    //   7: invokevirtual longValue : ()J
    //   10: lstore_2
    //   11: pop
    //   12: getstatic me/frep/aegisguard/spigot/aegisguard_R.a : J
    //   15: lload_2
    //   16: lxor
    //   17: lstore_2
    //   18: invokestatic aegisguard_P : ()[Lme/frep/aegisguard/spigot/check/AbstractCheck;
    //   21: astore #4
    //   23: aload_0
    //   24: getfield aegisguard_v : I
    //   27: aload #4
    //   29: ifnull -> 53
    //   32: iflt -> 81
    //   35: goto -> 42
    //   38: invokestatic a : (Ljava/lang/RuntimeException;)Ljava/lang/RuntimeException;
    //   41: athrow
    //   42: aload_0
    //   43: getfield aegisguard_v : I
    //   46: goto -> 53
    //   49: invokestatic a : (Ljava/lang/RuntimeException;)Ljava/lang/RuntimeException;
    //   52: athrow
    //   53: aload #4
    //   55: ifnull -> 78
    //   58: bipush #50
    //   60: if_icmpge -> 81
    //   63: goto -> 70
    //   66: invokestatic a : (Ljava/lang/RuntimeException;)Ljava/lang/RuntimeException;
    //   69: athrow
    //   70: iconst_1
    //   71: goto -> 78
    //   74: invokestatic a : (Ljava/lang/RuntimeException;)Ljava/lang/RuntimeException;
    //   77: athrow
    //   78: goto -> 82
    //   81: iconst_0
    //   82: ireturn
    // Line number table:
    //   Java source line number -> byte code offset
    //   #123	-> 23
    // Exception table:
    //   from	to	target	type
    //   23	35	38	java/lang/RuntimeException
    //   32	46	49	java/lang/RuntimeException
    //   53	63	66	java/lang/RuntimeException
    //   58	71	74	java/lang/RuntimeException
  }
  
  public float aegisguard_n(Object[] paramArrayOfObject) {
    double d1 = this.aegisguard_e.aegisguard_x(new Object[0]).aegisguard__(new Object[0]);
    double d2 = this.aegisguard_e.aegisguard_x(new Object[0]).aegisguard_m(new Object[0]);
    Vector vector1 = new Vector(d1, 0.0D, d2);
    Vector vector2 = new Vector(-Math.sin((this.aegisguard_d * 3.1415927F / 180.0F)) * 1.0D * 0.5D, 0.0D, Math.cos((this.aegisguard_d * 3.1415927F / 180.0F)) * 1.0D * 0.5D);
    return vector1.angle(vector2);
  }
  
  public static void aegisguard_I(int paramInt) {
    aegisguard_h = paramInt;
  }
  
  public static int aegisguard__() {
    return aegisguard_h;
  }
  
  public static int aegisguard_j() {
    int i = aegisguard__();
    try {
      if (i == 0)
        return 108; 
    } catch (RuntimeException runtimeException) {
      throw a(null);
    } 
    return 0;
  }
  
  static {
    if (aegisguard_j() == 0)
      aegisguard_I(74); 
  }
  
  private static RuntimeException a(RuntimeException paramRuntimeException) {
    return paramRuntimeException;
  }
}
