package me.frep.aegisguard.spigot.AegisGuard_Kd;

public final class Vulcan_Kd {
  public static final short Vulcan_c = -24768;
  
  public static final short Vulcan_Q = -23769;
  
  public static final short Vulcan_z = -30768;
  
  public static final short Vulcan_m = -29769;
  
  public static final short Vulcan_N = -29768;
  
  public static final short Vulcan_w = -28769;
  
  public static final short Vulcan_j = -28768;
  
  public static final short Vulcan_u = -27769;
  
  public static final short Vulcan_F = -27768;
  
  public static final short Vulcan_i = -26769;
  
  public static final short Vulcan__ = -26768;
  
  public static final short Vulcan_T = -25769;
  
  public static final short Vulcan_V = -23768;
  
  public static final short Vulcan_t = -22769;
  
  public static final short Vulcan_q = -22768;
  
  public static final short Vulcan_P = -21769;
  
  private static final String a;
  
  private Vulcan_Kd() {
    throw new UnsupportedOperationException(a);
  }
  
  static {
    // Byte code:
    //   0: bipush #65
    //   2: ldc 'Vfz{Kn4"o3}n+kzj(\\bk&q}3icgao}fsg`k3at3c`ga\\ns"f'
    //   4: iconst_m1
    //   5: goto -> 14
    //   8: putstatic me/frep/vulcan/spigot/Vulcan_Kd.a : Ljava/lang/String;
    //   11: goto -> 154
    //   14: dup_x2
    //   15: pop
    //   16: invokevirtual toCharArray : ()[C
    //   19: dup_x1
    //   20: arraylength
    //   21: dup_x2
    //   22: pop
    //   23: iconst_0
    //   24: istore_0
    //   25: dup2_x1
    //   26: pop2
    //   27: dup_x2
    //   28: iconst_1
    //   29: if_icmpgt -> 128
    //   32: dup2
    //   33: swap
    //   34: iload_0
    //   35: dup2_x1
    //   36: caload
    //   37: swap
    //   38: iload_0
    //   39: bipush #7
    //   41: irem
    //   42: tableswitch default -> 110, 0 -> 80, 1 -> 85, 2 -> 90, 3 -> 95, 4 -> 100, 5 -> 105
    //   80: bipush #67
    //   82: goto -> 112
    //   85: bipush #79
    //   87: goto -> 112
    //   90: bipush #82
    //   92: goto -> 112
    //   95: bipush #73
    //   97: goto -> 112
    //   100: bipush #42
    //   102: goto -> 112
    //   105: bipush #70
    //   107: goto -> 112
    //   110: bipush #6
    //   112: ixor
    //   113: ixor
    //   114: i2c
    //   115: castore
    //   116: iinc #0, 1
    //   119: dup
    //   120: ifne -> 128
    //   123: dup2
    //   124: dup_x1
    //   125: goto -> 35
    //   128: dup2_x1
    //   129: pop2
    //   130: dup_x2
    //   131: iload_0
    //   132: if_icmpgt -> 32
    //   135: pop
    //   136: new java/lang/String
    //   139: dup_x1
    //   140: swap
    //   141: invokespecial <init> : ([C)V
    //   144: invokevirtual intern : ()Ljava/lang/String;
    //   147: swap
    //   148: pop
    //   149: swap
    //   150: pop
    //   151: goto -> 8
    //   154: return
  }
}
